cdns/__init__.py
cdns/__main__.py
cdns/cache.py
cdns/daemon.py
cdns/manager.py
cdns/protocol.py
cdns/resolver.py
cdns/storage.py
cdns/utils.py
cdns/zones.py
cdns/_installer/__init__.py
cdns/_installer/macos.py
cdns/_installer/data/__init__.py
cdns/_installer/data/com.ninjamar.compactdns.plist
cdns/_installer/data/com.ninjamar.sleepwatcher-root-cdns.plist
cdns/_installer/data/macos_watcher.sh
cdns/_installer/data/sleepwatcher-root.sh
cdns/cli/__init__.py
cdns/cli/cli.py
cdns/cli/kwargs.py
cdns/lcb/__init__.py
cdns/lcb/lcb.py
cdns/response/__init__.py
cdns/response/mixins.py
cdns/response/response.py
cdns/response/timer.py
cdns/tools/__init__.py
cdns/tools/h2j.py
cdns/tools/shell_client.py
compactdns-0.1.0a6.dist-info/licenses/LICENSE
compactdns-0.1.0a6.dist-info/METADATA
compactdns-0.1.0a6.dist-info/WHEEL
compactdns-0.1.0a6.dist-info/entry_points.txt
compactdns-0.1.0a6.dist-info/top_level.txt
compactdns-0.1.0a6.dist-info/RECORD
