Metadata-Version: 2.4
Name: compactdns
Version: 0.1.0a6
Summary: CompactDNS (CDNS) is a minimalistic yet powerful DNS server designed for simplicity and speed.
Author: ninjamar
License: MIT License
Project-URL: Homepage, https://github.com/ninjamar/compactdns
Project-URL: Repository, https://github.com/ninjamar/compactdns
Project-URL: Issues, https://github.com/ninjamar/compactdns/issues
Keywords: dns,privacy,dns-server,adblocker,dns-over-tls
Classifier: Development Status :: 3 - Alpha
Classifier: Operating System :: MacOS
Classifier: Operating System :: POSIX
Classifier: Operating System :: Microsoft :: Windows
Classifier: Programming Language :: Python :: 3 :: Only
Classifier: Programming Language :: Python :: 3
Classifier: Programming Language :: Python :: 3.10
Classifier: Programming Language :: Python :: 3.11
Classifier: Programming Language :: Python :: 3.12
Classifier: Topic :: Communications
Classifier: Topic :: Internet
Classifier: Topic :: Internet :: Name Service (DNS)
Classifier: Typing :: Typed
Requires-Python: >=3.10
License-File: LICENSE
Requires-Dist: publicsuffixlist>=1.0
Requires-Dist: tomli>=1.0; python_version < "3.11"
Dynamic: license-file
